[
  {
    "version": "1.133.0",
    "url_download_runtime": "https://github.com/SAP/openui5/releases/download/1.133.0/openui5-runtime-1.133.0.zip",
    "url_download_sdk": "https://github.com/SAP/openui5/releases/download/1.133.0/openui5-sdk-1.133.0.zip",
    "url_download_mobile": "https://github.com/SAP/openui5/releases/download/1.133.0/openui5-runtime-mobile-1.133.0.zip",
    "url_demokit": "https://sdk.openui5.org/1.133.0/#/topic/99ac68a5b1c3416ab5c84c99fefa250d",
    "url_releasenotes": "https://sdk.openui5.org/1.133.0/#releasenotes.html",
    "release_date": "18.02.2025",
    "eom": ""
  },
  {
    "version": "1.130.5",
    "url_download_runtime": "https://github.com/SAP/openui5/releases/download/1.130.5/openui5-runtime-1.130.5.zip",
    "url_download_sdk": "https://github.com/SAP/openui5/releases/download/1.130.5/openui5-sdk-1.130.5.zip",
    "url_download_mobile": "https://github.com/SAP/openui5/releases/download/1.130.5/openui5-runtime-mobile-1.130.5.zip",
    "url_demokit": "https://sdk.openui5.org/1.130.5/#/topic/99ac68a5b1c3416ab5c84c99fefa250d",
    "url_releasenotes": "https://sdk.openui5.org/1.130.5/#releasenotes.html",
    "release_date": "24.02.2025",
    "eom": ""
  },
  {
    "version": "1.127.5",
    "url_download_runtime": "https://github.com/SAP/openui5/releases/download/1.127.5/openui5-runtime-1.127.5.zip",
    "url_download_sdk": "https://github.com/SAP/openui5/releases/download/1.127.5/openui5-sdk-1.127.5.zip",
    "url_download_mobile": "https://github.com/SAP/openui5/releases/download/1.127.5/openui5-runtime-mobile-1.127.5.zip",
    "url_demokit": "https://sdk.openui5.org/1.127.5/#/topic/99ac68a5b1c3416ab5c84c99fefa250d",
    "url_releasenotes": "https://sdk.openui5.org/1.127.5/#releasenotes.html",
    "release_date": "26.11.2024",
    "eom": ""
  },
  {
    "version": "1.124.9",
    "url_download_runtime": "https://github.com/SAP/openui5/releases/download/1.124.9/openui5-runtime-1.124.9.zip",
    "url_download_sdk": "https://github.com/SAP/openui5/releases/download/1.124.9/openui5-sdk-1.124.9.zip",
    "url_download_mobile": "https://github.com/SAP/openui5/releases/download/1.124.9/openui5-runtime-mobile-1.124.9.zip",
    "url_demokit": "https://sdk.openui5.org/1.124.9/#/topic/99ac68a5b1c3416ab5c84c99fefa250d",
    "url_releasenotes": "https://sdk.openui5.org/1.124.9/#releasenotes.html",
    "release_date": "25.11.2024",
    "eom": ""
  },
  {
    "version": "1.120.27",
    "url_download_runtime": "https://github.com/SAP/openui5/releases/download/1.120.27/openui5-runtime-1.120.27.zip",
    "url_download_sdk": "https://github.com/SAP/openui5/releases/download/1.120.27/openui5-sdk-1.120.27.zip",
    "url_download_mobile": "https://github.com/SAP/openui5/releases/download/1.120.27/openui5-runtime-mobile-1.120.27.zip",
    "url_demokit": "https://sdk.openui5.org/1.120.27/#/topic/99ac68a5b1c3416ab5c84c99fefa250d",
    "url_releasenotes": "https://sdk.openui5.org/1.120.27/#releasenotes.html",
    "release_date": "27.02.2025",
    "eom": "Q4/2030"
  },
  {
    "version": "1.108.40",
    "url_download_runtime": "https://github.com/SAP/openui5/releases/download/1.108.40/openui5-runtime-1.108.40.zip",
    "url_download_sdk": "https://github.com/SAP/openui5/releases/download/1.108.40/openui5-sdk-1.108.40.zip",
    "url_download_mobile": "https://github.com/SAP/openui5/releases/download/1.108.40/openui5-runtime-mobile-1.108.40.zip",
    "url_demokit": "https://sdk.openui5.org/1.108.40/#/topic/99ac68a5b1c3416ab5c84c99fefa250d",
    "url_releasenotes": "https://sdk.openui5.org/1.108.40/#releasenotes.html",
    "release_date": "10.03.2025",
    "eom": "Q4/2030"
  },
  {
    "version": "1.96.38",
    "url_download_runtime": "https://github.com/SAP/openui5/releases/download/1.96.38/openui5-runtime-1.96.38.zip",
    "url_download_sdk": "https://github.com/SAP/openui5/releases/download/1.96.38/openui5-sdk-1.96.38.zip",
    "url_download_mobile": "https://github.com/SAP/openui5/releases/download/1.96.38/openui5-runtime-mobile-1.96.38.zip",
    "url_demokit": "https://sdk.openui5.org/1.96.38/#/topic/99ac68a5b1c3416ab5c84c99fefa250d",
    "url_releasenotes": "https://sdk.openui5.org/1.96.38/#releasenotes.html",
    "release_date": "05.03.2025",
    "eom": "Q4/2026"
  },
  {
    "version": "1.84.50",
    "url_download_runtime": "https://github.com/SAP/openui5/releases/download/1.84.50/openui5-runtime-1.84.50.zip",
    "url_download_sdk": "https://github.com/SAP/openui5/releases/download/1.84.50/openui5-sdk-1.84.50.zip",
    "url_download_mobile": "https://github.com/SAP/openui5/releases/download/1.84.50/openui5-runtime-mobile-1.84.50.zip",
    "url_demokit": "https://sdk.openui5.org/1.84.50/#/topic/99ac68a5b1c3416ab5c84c99fefa250d",
    "url_releasenotes": "https://sdk.openui5.org/1.84.50/#releasenotes.html",
    "release_date": "17.03.2025",
    "eom": "Q4/2025"
  },
  {
    "version": "1.71.70",
    "url_download_runtime": "https://github.com/SAP/openui5/releases/download/1.71.70/openui5-runtime-1.71.70.zip",
    "url_download_sdk": "https://github.com/SAP/openui5/releases/download/1.71.70/openui5-sdk-1.71.70.zip",
    "url_download_mobile": "https://github.com/SAP/openui5/releases/download/1.71.70/openui5-runtime-mobile-1.71.70.zip",
    "url_demokit": "https://sdk.openui5.org/1.71.70/#/topic/99ac68a5b1c3416ab5c84c99fefa250d",
    "url_releasenotes": "https://sdk.openui5.org/1.71.70/#releasenotes.html",
    "release_date": "25.02.2025",
    "eom": "Q4/2030"
  },
  {
    "version": "1.38.64",
    "url_download_runtime": "https://github.com/SAP/openui5/releases/download/1.38.64/openui5-runtime-1.38.64.zip",
    "url_download_sdk": "https://github.com/SAP/openui5/releases/download/1.38.64/openui5-sdk-1.38.64.zip",
    "url_download_mobile": "https://github.com/SAP/openui5/releases/download/1.38.64/openui5-runtime-mobile-1.38.64.zip",
    "url_demokit": "https://sdk.openui5.org/1.38.64/#/topic/99ac68a5b1c3416ab5c84c99fefa250d",
    "url_releasenotes": "https://sdk.openui5.org/1.38.64/#releasenotes.html",
    "release_date": "24.02.2025",
    "eom": "Q4/2027"
  }
]