[
  {
    "version": "1.140.0",
    "url_download_runtime": "https://github.com/UI5/openui5/releases/download/1.140.0/openui5-runtime-1.140.0.zip",
    "url_download_sdk": "https://github.com/UI5/openui5/releases/download/1.140.0/openui5-sdk-1.140.0.zip",
    "url_download_mobile": "https://github.com/UI5/openui5/releases/download/1.140.0/openui5-runtime-mobile-1.140.0.zip",
    "url_demokit": "https://sdk.openui5.org/1.140.0/#/topic/99ac68a5b1c3416ab5c84c99fefa250d",
    "url_releasenotes": "https://sdk.openui5.org/1.140.0/#releasenotes.html",
    "release_date": "01.09.2025",
    "eom": ""
  },
  {
    "version": "1.136.6",
    "url_download_runtime": "https://github.com/UI5/openui5/releases/download/1.136.6/openui5-runtime-1.136.6.zip",
    "url_download_sdk": "https://github.com/UI5/openui5/releases/download/1.136.6/openui5-sdk-1.136.6.zip",
    "url_download_mobile": "https://github.com/UI5/openui5/releases/download/1.136.6/openui5-runtime-mobile-1.136.6.zip",
    "url_demokit": "https://sdk.openui5.org/1.136.6/#/topic/99ac68a5b1c3416ab5c84c99fefa250d",
    "url_releasenotes": "https://sdk.openui5.org/1.136.6/#releasenotes.html",
    "release_date": "03.09.2025",
    "eom": "Q3/2026"
  },
  {
    "version": "1.120.34",
    "url_download_runtime": "https://github.com/UI5/openui5/releases/download/1.120.34/openui5-runtime-1.120.34.zip",
    "url_download_sdk": "https://github.com/UI5/openui5/releases/download/1.120.34/openui5-sdk-1.120.34.zip",
    "url_download_mobile": "https://github.com/UI5/openui5/releases/download/1.120.34/openui5-runtime-mobile-1.120.34.zip",
    "url_demokit": "https://sdk.openui5.org/1.120.34/#/topic/99ac68a5b1c3416ab5c84c99fefa250d",
    "url_releasenotes": "https://sdk.openui5.org/1.120.34/#releasenotes.html",
    "release_date": "19.08.2025",
    "eom": "Q4/2030"
  },
  {
    "version": "1.108.43",
    "url_download_runtime": "https://github.com/UI5/openui5/releases/download/1.108.43/openui5-runtime-1.108.43.zip",
    "url_download_sdk": "https://github.com/UI5/openui5/releases/download/1.108.43/openui5-sdk-1.108.43.zip",
    "url_download_mobile": "https://github.com/UI5/openui5/releases/download/1.108.43/openui5-runtime-mobile-1.108.43.zip",
    "url_demokit": "https://sdk.openui5.org/1.108.43/#/topic/99ac68a5b1c3416ab5c84c99fefa250d",
    "url_releasenotes": "https://sdk.openui5.org/1.108.43/#releasenotes.html",
    "release_date": "21.07.2025",
    "eom": "Q4/2030"
  },
  {
    "version": "1.96.41",
    "url_download_runtime": "https://github.com/UI5/openui5/releases/download/1.96.41/openui5-runtime-1.96.41.zip",
    "url_download_sdk": "https://github.com/UI5/openui5/releases/download/1.96.41/openui5-sdk-1.96.41.zip",
    "url_download_mobile": "https://github.com/UI5/openui5/releases/download/1.96.41/openui5-runtime-mobile-1.96.41.zip",
    "url_demokit": "https://sdk.openui5.org/1.96.41/#/topic/99ac68a5b1c3416ab5c84c99fefa250d",
    "url_releasenotes": "https://sdk.openui5.org/1.96.41/#releasenotes.html",
    "release_date": "25.08.2025",
    "eom": "Q4/2026"
  },
  {
    "version": "1.84.51",
    "url_download_runtime": "https://github.com/UI5/openui5/releases/download/1.84.51/openui5-runtime-1.84.51.zip",
    "url_download_sdk": "https://github.com/UI5/openui5/releases/download/1.84.51/openui5-sdk-1.84.51.zip",
    "url_download_mobile": "https://github.com/UI5/openui5/releases/download/1.84.51/openui5-runtime-mobile-1.84.51.zip",
    "url_demokit": "https://sdk.openui5.org/1.84.51/#/topic/99ac68a5b1c3416ab5c84c99fefa250d",
    "url_releasenotes": "https://sdk.openui5.org/1.84.51/#releasenotes.html",
    "release_date": "30.06.2025",
    "eom": "Q4/2025"
  },
  {
    "version": "1.71.72",
    "url_download_runtime": "https://github.com/UI5/openui5/releases/download/1.71.72/openui5-runtime-1.71.72.zip",
    "url_download_sdk": "https://github.com/UI5/openui5/releases/download/1.71.72/openui5-sdk-1.71.72.zip",
    "url_download_mobile": "https://github.com/UI5/openui5/releases/download/1.71.72/openui5-runtime-mobile-1.71.72.zip",
    "url_demokit": "https://sdk.openui5.org/1.71.72/#/topic/99ac68a5b1c3416ab5c84c99fefa250d",
    "url_releasenotes": "https://sdk.openui5.org/1.71.72/#releasenotes.html",
    "release_date": "22.07.2025",
    "eom": "Q4/2030"
  },
  {
    "version": "1.38.65",
    "url_download_runtime": "https://github.com/UI5/openui5/releases/download/1.38.65/openui5-runtime-1.38.65.zip",
    "url_download_sdk": "https://github.com/UI5/openui5/releases/download/1.38.65/openui5-sdk-1.38.65.zip",
    "url_download_mobile": "https://github.com/UI5/openui5/releases/download/1.38.65/openui5-runtime-mobile-1.38.65.zip",
    "url_demokit": "https://sdk.openui5.org/1.38.65/#/topic/99ac68a5b1c3416ab5c84c99fefa250d",
    "url_releasenotes": "https://sdk.openui5.org/1.38.65/#releasenotes.html",
    "release_date": "07.05.2025",
    "eom": "Q4/2027"
  }
]